gumc.py
gums.py
gums-0.0.33.data/scripts/gumc
gums-0.0.33.data/scripts/gums
gums-0.0.33.dist-info/LICENSE
gums-0.0.33.dist-info/METADATA
gums-0.0.33.dist-info/WHEEL
gums-0.0.33.dist-info/top_level.txt
gums-0.0.33.dist-info/RECORD
