Metadata-Version: 2.1
Name: gums
Version: 0.0.33
Summary: gums, Grande Unicast Multicast Sender
Home-page: https://github.com/futzu/gums
Author: Adrian
Author-email: spam@iodisco.com
License: UNKNOWN
Platform: all
Classifier: License :: OSI Approved :: MIT License
Classifier: Operating System :: OS Independent
Classifier: Programming Language :: Python :: 3.6
Classifier: Programming Language :: Python :: Implementation :: PyPy
Classifier: Programming Language :: Python :: Implementation :: CPython
Requires-Python: >=3.6
Requires-Dist: new-reader (>=0.1.13)
